README
git_branchdescriptions.py
setup.py
git_branchdescriptions.egg-info/PKG-INFO
git_branchdescriptions.egg-info/SOURCES.txt
git_branchdescriptions.egg-info/dependency_links.txt
git_branchdescriptions.egg-info/entry_points.txt
git_branchdescriptions.egg-info/not-zip-safe
git_branchdescriptions.egg-info/requires.txt
git_branchdescriptions.egg-info/top_level.txt