Metadata-Version: 1.0
Name: git-branchdescriptions
Version: 0.0.2
Summary: git-branchdescriptions
Home-page: http://github.com/traviscline/git-branchdescriptions/
Author: Travis Cline
Author-email: travis.cline@gmail.com
License: MIT
Platform: any
Classifier: Intended Audience :: Developers
Classifier: License :: OSI Approved :: MIT License
Classifier: Development Status :: 3 - Alpha
